CHANGELOG.txt
LICENSE.txt
MANIFEST.in
README.txt
setup.py
RJtrusst/__init__.py
RJtrusst.egg-info/PKG-INFO
RJtrusst.egg-info/SOURCES.txt
RJtrusst.egg-info/dependency_links.txt
RJtrusst.egg-info/top_level.txt